squad_client/__init__.py
squad_client/exceptions.py
squad_client/logging.py
squad_client/manage.py
squad_client/report.py
squad_client/settings.py
squad_client/shortcuts.py
squad_client/utils.py
squad_client/version.py
squad_client/commands/__init__.py
squad_client/commands/create_or_update_project.py
squad_client/commands/download_attachments.py
squad_client/commands/download_results.py
squad_client/commands/register_callback.py
squad_client/commands/report.py
squad_client/commands/shell.py
squad_client/commands/submit.py
squad_client/commands/submit_job.py
squad_client/commands/submit_tuxbuild.py
squad_client/commands/submit_tuxsuite.py
squad_client/commands/test.py
squad_client/core/api.py
squad_client/core/command.py
squad_client/core/models.py
squad_client-0.45.dist-info/LICENSE
squad_client-0.45.dist-info/METADATA
squad_client-0.45.dist-info/WHEEL
squad_client-0.45.dist-info/entry_points.txt
squad_client-0.45.dist-info/top_level.txt
squad_client-0.45.dist-info/RECORD
