Metadata-Version: 2.2
Name: squad-client
Version: 0.45
Summary: Client for SQUAD
Home-page: https://github.com/Linaro/squad-client
Author: Charles Oliveira
Author-email: charles.oliveira@linaro.org
License: MIT
Platform: any
Requires-Python: >=3.6
License-File: LICENSE
Requires-Dist: requests
Requires-Dist: requests_cache
Requires-Dist: jinja2
Requires-Dist: jsonschema
Requires-Dist: ipython
Requires-Dist: pyyaml
Dynamic: author
Dynamic: author-email
Dynamic: description
Dynamic: home-page
Dynamic: license
Dynamic: platform
Dynamic: requires-dist
Dynamic: requires-python
Dynamic: summary
